hdstats/__init__.py
hdstats/dtw.c
hdstats/dtw.cpython-39-darwin.so
hdstats/dtw.pyx
hdstats/geomad.c
hdstats/geomad.cpython-39-darwin.so
hdstats/geomad.pyx
hdstats/geomedian.c
hdstats/geomedian.cpython-39-darwin.so
hdstats/geomedian.pyx
hdstats/ts.c
hdstats/ts.cpython-39-darwin.so
hdstats/ts.pyx
hdstats/tsslow.py
hdstats/utils.py
hdstats-0.2.dist-info/LICENSE
hdstats-0.2.dist-info/METADATA
hdstats-0.2.dist-info/WHEEL
hdstats-0.2.dist-info/top_level.txt
hdstats-0.2.dist-info/RECORD
