Metadata-Version: 2.1
Name: hdstats
Version: 0.2
Summary: Multivariate / high-dimensional statistics and time series algorithms for spatial-temporal stacks
Home-page: http://github.com/daleroberts/hdstats
Author: Dale Roberts
Author-email: dale.o.roberts@gmail.com
License: BSD-3-Clause License
Platform: UNKNOWN
Requires-Dist: numpy
Requires-Dist: scipy
Provides-Extra: test
Requires-Dist: pytest ; extra == 'test'
Requires-Dist: joblib ; extra == 'test'
